mnspy/__init__.py
mnspy/utilidades.py
mnspy/derivada/__init__.py
mnspy/derivada/derivada.py
mnspy/derivada/derivada_discreta.py
mnspy/derivada/richardson.py
mnspy/ecuaciones_algebraicas_lineales/__init__.py
mnspy/ecuaciones_algebraicas_lineales/cramer.py
mnspy/ecuaciones_algebraicas_lineales/descomposicion_LU.py
mnspy/ecuaciones_algebraicas_lineales/descomposicion_cholesky.py
mnspy/ecuaciones_algebraicas_lineales/ecuaciones_algebraicas_lineales.py
mnspy/ecuaciones_algebraicas_lineales/gauss.py
mnspy/ecuaciones_algebraicas_lineales/gauss_jordan.py
mnspy/ecuaciones_algebraicas_lineales/gauss_sediel.py
mnspy/ecuaciones_algebraicas_lineales/tridiagonal.py
mnspy/ecuaciones_diferenciales_ordinarias/__init__.py
mnspy/ecuaciones_diferenciales_ordinarias/ecuaciones_diferenciales_ordinarias.py
mnspy/ecuaciones_diferenciales_ordinarias/euler.py
mnspy/ecuaciones_diferenciales_ordinarias/heun.py
mnspy/ecuaciones_diferenciales_ordinarias/punto_medio.py
mnspy/ecuaciones_diferenciales_ordinarias/runge_kutta.py
mnspy/ecuaciones_diferenciales_parciales/__init__.py
mnspy/ecuaciones_diferenciales_parciales/ecuaciones_diferenciales_parciales.py
mnspy/ecuaciones_diferenciales_parciales/liebmann.py
mnspy/ecuaciones_diferenciales_parciales/mdf/__init__.py
mnspy/ecuaciones_diferenciales_parciales/mdf/mdf.py
mnspy/ecuaciones_diferenciales_parciales/mef/__init__.py
mnspy/ecuaciones_diferenciales_parciales/mef/armadura.py
mnspy/ecuaciones_diferenciales_parciales/mef/barra.py
mnspy/ecuaciones_diferenciales_parciales/mef/ensamble.py
mnspy/ecuaciones_diferenciales_parciales/mef/marco.py
mnspy/ecuaciones_diferenciales_parciales/mef/mef.py
mnspy/ecuaciones_diferenciales_parciales/mef/resorte.py
mnspy/ecuaciones_diferenciales_parciales/mef/triangular_cst.py
mnspy/ecuaciones_diferenciales_parciales/mef/viga.py
mnspy/ecuaciones_diferenciales_parciales/mvf/__init__.py
mnspy/ecuaciones_diferenciales_parciales/mvf/mvf.py
mnspy/ecuaciones_diferenciales_parciales/mvf/volumen_finito.py
mnspy-0.9.22.dist-info/licenses/LICENSE
mnspy-0.9.22.dist-info/METADATA
mnspy-0.9.22.dist-info/WHEEL
mnspy-0.9.22.dist-info/top_level.txt
mnspy-0.9.22.dist-info/RECORD
