Metadata-Version: 2.4
Name: mnspy
Version: 0.9.22
Summary: Paquete didáctico para métodos numéricos
Home-page: https://github.com/EdwinSoft/mnspy
Author: Edwin Córdoba
Author-email: edwin.cordoba@gmail.com
License: MIT
Requires-Python: >=3.10
License-File: LICENSE
Requires-Dist: scipy
Requires-Dist: sympy
Requires-Dist: matplotlib
Requires-Dist: tabulate
Requires-Dist: ipython
Requires-Dist: ipympl
Requires-Dist: jupyterlab-myst
Requires-Dist: jupyterlab-language-pack-es-ES
Requires-Dist: PyQt6
Requires-Dist: pandas
Requires-Dist: gmsh
Requires-Dist: openpyxl
Dynamic: author
Dynamic: author-email
Dynamic: description
Dynamic: description-content-type
Dynamic: home-page
Dynamic: license
Dynamic: license-file
Dynamic: requires-dist
Dynamic: requires-python
Dynamic: summary
